qwiic_soil_moisture_sensor.py
sparkfun_qwiic_soil_moisture_sensor-0.0.2.dist-info/LICENSE
sparkfun_qwiic_soil_moisture_sensor-0.0.2.dist-info/METADATA
sparkfun_qwiic_soil_moisture_sensor-0.0.2.dist-info/WHEEL
sparkfun_qwiic_soil_moisture_sensor-0.0.2.dist-info/top_level.txt
sparkfun_qwiic_soil_moisture_sensor-0.0.2.dist-info/RECORD
